text2api/__init__.py
text2api/cli.py
text2api/generators/__init__.py
text2api/generators/base_generator.py
text2api/generators/cli_gen.py
text2api/generators/client_generator.py
text2api/generators/factory.py
text2api/generators/fastapi_generator.py
text2api/generators/openapi_generator.py
text2api/generators/templates/README.md.j2
text2api/generators/templates/cli.py.j2
text2api/generators/templates/client/python/client.py.j2
text2api/generators/templates/client/typescript/client.ts.j2
text2api/generators/templates/fastapi/Dockerfile.j2
text2api/generators/templates/fastapi/main.py.j2
text2api/generators/templates/fastapi/models.py.j2
text2api/generators/templates/fastapi/models_fixed.py.j2
text2api/generators/templates/fastapi/models_new.py.j2
text2api/generators/templates/fastapi/router.py.j2
text2api/generators/templates/fastapi_main.py.j2
text2api/generators/templates/flask_app.py.j2
text2api/generators/templates/graphql_app.py.j2
text2api/generators/templates/grpc_proto.proto.j2
text2api/generators/templates/requirements.txt.j2
text2api/generators/templates/websocket_server.py.j2
text2api/nlp/spec_extractor.py
text2api-0.1.7.dist-info/LICENSE
text2api-0.1.7.dist-info/METADATA
text2api-0.1.7.dist-info/WHEEL
text2api-0.1.7.dist-info/entry_points.txt
text2api-0.1.7.dist-info/RECORD
