Metadata-Version: 2.3
Name: text2api
Version: 0.1.7
Summary: Automatyczne generowanie API na podstawie opisu tekstowego z wykorzystaniem NLP i Ollama
Author: Tom Sapletta
Author-email: info@softreck.dev
Requires-Python: >=3.10,<4.0
Classifier: Programming Language :: Python :: 3
Classifier: Programming Language :: Python :: 3.10
Classifier: Programming Language :: Python :: 3.11
Classifier: Programming Language :: Python :: 3.12
Classifier: Programming Language :: Python :: 3.13
Requires-Dist: aiofiles (>=23.2.1,<24.0.0)
Requires-Dist: asyncio (>=3.4.3,<4.0.0)
Requires-Dist: black (>=23.1.0,<24.0.0)
Requires-Dist: click (>=8.1.7,<9.0.0)
Requires-Dist: docker (>=6.1.3,<7.0.0)
Requires-Dist: fastapi (>=0.112.0,<0.113.0)
Requires-Dist: flake8 (>=6.1.0,<7.0.0)
Requires-Dist: flask (>=3.0.0,<4.0.0)
Requires-Dist: flask-restx (>=1.3.0,<2.0.0)
Requires-Dist: graphene (>=3.3.0,<4.0.0)
Requires-Dist: grpcio (>=1.60.0,<2.0.0)
Requires-Dist: grpcio-tools (>=1.60.0,<2.0.0)
Requires-Dist: httpx (>=0.27.0,<0.28.0)
Requires-Dist: isort (>=5.12.0,<6.0.0)
Requires-Dist: jinja2 (>=3.1.2,<4.0.0)
Requires-Dist: langdetect (>=1.0.9,<2.0.0)
Requires-Dist: mcp (>=1.0.0,<2.0.0)
Requires-Dist: mypy (>=1.6.1,<2.0.0)
Requires-Dist: ollama (>=0.3.0,<0.4.0)
Requires-Dist: pydantic (>=2.5.0,<3.0.0)
Requires-Dist: pytest (>=7.4.0,<8.0.0)
Requires-Dist: python-multipart (>=0.0.9,<0.0.10)
Requires-Dist: pyyaml (>=6.0.1,<7.0.0)
Requires-Dist: rich (>=13.7.0,<14.0.0)
Requires-Dist: spacy (>=3.7.2,<4.0.0)
Requires-Dist: starlette (>=0.38.0,<0.39.0)
Requires-Dist: uvicorn (>=0.30.0,<0.31.0)
Requires-Dist: websockets (>=12.0,<13.0)
